yupdates/__init__.py
yupdates/client.py
yupdates/models.py
yupdates/yapi.py
yupdates-0.1.1.dist-info/LICENSE
yupdates-0.1.1.dist-info/METADATA
yupdates-0.1.1.dist-info/WHEEL
yupdates-0.1.1.dist-info/top_level.txt
yupdates-0.1.1.dist-info/RECORD
