Metadata-Version: 2.1
Name: yupdates
Version: 0.1.1
Summary: Yupdates Python SDK
Home-page: https://github.com/yupdates/yupdates-sdk-py
Author: Reed Bend Software, Inc.
Author-email: tim@yupdates.com
Project-URL: Tracker, https://github.com/yupdates/yupdates-sdk-py/issues
Classifier: Programming Language :: Python :: 3
Classifier: License :: OSI Approved :: MIT License
Classifier: Operating System :: OS Independent
Requires-Python: >=3.7
License-File: LICENSE
